{
  "project_info": {
    "project_number": "505935158307",
    "firebase_url": "https://my-recipe-book-a9511.firebaseio.com",
    "project_id": "my-recipe-book-a9511",
    "storage_bucket": "my-recipe-book-a9511.appspot.com"
  },
  "client": [
    {
      "client_info": {
        "mobilesdk_app_id": "1:505935158307:android:4e75385e2d55782b",
        "android_client_info": {
          "package_name": "com.eleven.group.myrecipiebook"
        }
      },
      "oauth_client": [
        {
          "client_id": "505935158307-dnbg833k4s9mrkesuplml5gh8i64a6ht.apps.googleusercontent.com",
          "client_type": 1,
          "android_info": {
            "package_name": "com.eleven.group.myrecipiebook",
            "certificate_hash": "ef4829f8ad7fd58c9eae489e24d043f8fd547a53"
          }
        },
        {
          "client_id": "505935158307-67b5onk7dridngne52ta0g443oq7s3d0.apps.googleusercontent.com",
          "client_type": 3
        }
      ],
      "api_key": [
        {
          "current_key": "AIzaSyDtQ_uimenSp9XGtRo0iVyHMRxXczIUVEw"
        }
      ],
      "services": {
        "analytics_service": {
          "status": 1
        },
        "appinvite_service": {
          "status": 2,
          "other_platform_oauth_client": [
            {
              "client_id": "505935158307-67b5onk7dridngne52ta0g443oq7s3d0.apps.googleusercontent.com",
              "client_type": 3
            }
          ]
        },
        "ads_service": {
          "status": 2
        }
      }
    }
  ],
  "configuration_version": "1"
}